{
  "users": [
    {
      "name": "Михаил",
      "surname": "Стругацкий",
      "gender": "male",
      "id": 11
    },
    {
      "name": "Аби",
      "surname": "Кошка",
      "gender": "other",
      "id": 20
    },
    {
      "name": "Джек",
      "surname": "Воробей",
      "gender": "other",
      "id": 21
    },
    {
      "name": "Гарри",
      "surname": "Поттер",
      "gender": "male",
      "id": 22
    },
    {
      "name": "Джекки",
      "surname": "Чан",
      "gender": "male",
      "id": 23
    },
    {
      "name": "Войко",
      "surname": "Митич",
      "gender": "male",
      "id": 24
    }
  ]
}